{"dependencies":[{"name":"C:\\Users\\brenn\\OneDrive - BYU-Idaho\\CIT 261\\portfolio\\parcel\\.babelrc","includedInParent":true,"mtime":1528818892602},{"name":"C:\\Users\\brenn\\OneDrive - BYU-Idaho\\CIT 261\\portfolio\\parcel\\package.json","includedInParent":true,"mtime":1528818892729},{"name":"./ships","loc":{"line":1,"column":27}}],"generated":{"js":"'use strict';\n\nvar _ships = require('./ships');\n\nvar _ships2 = _interopRequireDefault(_ships);\n\nfunction _interopRequireDefault(obj) { return obj && obj.__esModule ? obj : { default: obj }; }\n\nconsole.log(_ships2.default.getShips());\nconsole.log(_ships2.default.getShipByName('Executor'));\n\n// check to see if javascript is working\nfunction component() {\n  var element = document.createElement('p');\n\n  element.innerHTML = 'Setup Appears to be working &#128521;';\n\n  return element;\n}\ndocument.body.appendChild(component());\n\n// shipController.getShips().then((data) => {\n//   console.log(data);\n// });","map":{"mappings":[{"generated":{"line":3,"column":0},"source":"js\\index.js","original":{"line":1,"column":0}},{"name":"console","generated":{"line":9,"column":0},"source":"js\\index.js","original":{"line":3,"column":0}},{"name":"log","generated":{"line":9,"column":8},"source":"js\\index.js","original":{"line":3,"column":8}},{"generated":{"line":9,"column":11},"source":"js\\index.js","original":{"line":3,"column":0}},{"generated":{"line":9,"column":12},"source":"js\\index.js","original":{"line":3,"column":12}},{"name":"getShips","generated":{"line":9,"column":28},"source":"js\\index.js","original":{"line":3,"column":27}},{"generated":{"line":9,"column":36},"source":"js\\index.js","original":{"line":3,"column":12}},{"generated":{"line":9,"column":38},"source":"js\\index.js","original":{"line":3,"column":0}},{"name":"console","generated":{"line":10,"column":0},"source":"js\\index.js","original":{"line":4,"column":0}},{"name":"log","generated":{"line":10,"column":8},"source":"js\\index.js","original":{"line":4,"column":8}},{"generated":{"line":10,"column":11},"source":"js\\index.js","original":{"line":4,"column":0}},{"generated":{"line":10,"column":12},"source":"js\\index.js","original":{"line":4,"column":12}},{"name":"getShipByName","generated":{"line":10,"column":28},"source":"js\\index.js","original":{"line":4,"column":27}},{"generated":{"line":10,"column":41},"source":"js\\index.js","original":{"line":4,"column":12}},{"generated":{"line":10,"column":42},"source":"js\\index.js","original":{"line":4,"column":41}},{"generated":{"line":10,"column":52},"source":"js\\index.js","original":{"line":4,"column":12}},{"generated":{"line":10,"column":53},"source":"js\\index.js","original":{"line":4,"column":0}},{"generated":{"line":12,"column":0},"source":"js\\index.js","original":{"line":6,"column":0}},{"generated":{"line":13,"column":0},"source":"js\\index.js","original":{"line":7,"column":0}},{"name":"component","generated":{"line":13,"column":9},"source":"js\\index.js","original":{"line":7,"column":9}},{"generated":{"line":13,"column":18},"source":"js\\index.js","original":{"line":7,"column":0}},{"generated":{"line":13,"column":21},"source":"js\\index.js","original":{"line":7,"column":21}},{"generated":{"line":14,"column":0},"source":"js\\index.js","original":{"line":8,"column":2}},{"name":"element","generated":{"line":14,"column":6},"source":"js\\index.js","original":{"line":8,"column":8}},{"name":"document","generated":{"line":14,"column":16},"source":"js\\index.js","original":{"line":8,"column":18}},{"name":"createElement","generated":{"line":14,"column":25},"source":"js\\index.js","original":{"line":8,"column":27}},{"generated":{"line":14,"column":38},"source":"js\\index.js","original":{"line":8,"column":18}},{"generated":{"line":14,"column":39},"source":"js\\index.js","original":{"line":8,"column":41}},{"generated":{"line":14,"column":42},"source":"js\\index.js","original":{"line":8,"column":18}},{"generated":{"line":14,"column":43},"source":"js\\index.js","original":{"line":8,"column":2}},{"name":"element","generated":{"line":16,"column":0},"source":"js\\index.js","original":{"line":10,"column":2}},{"name":"innerHTML","generated":{"line":16,"column":10},"source":"js\\index.js","original":{"line":10,"column":10}},{"generated":{"line":16,"column":19},"source":"js\\index.js","original":{"line":10,"column":2}},{"generated":{"line":16,"column":22},"source":"js\\index.js","original":{"line":10,"column":22}},{"generated":{"line":16,"column":61},"source":"js\\index.js","original":{"line":10,"column":2}},{"generated":{"line":18,"column":0},"source":"js\\index.js","original":{"line":12,"column":2}},{"name":"element","generated":{"line":18,"column":9},"source":"js\\index.js","original":{"line":12,"column":9}},{"generated":{"line":18,"column":16},"source":"js\\index.js","original":{"line":12,"column":2}},{"generated":{"line":19,"column":0},"source":"js\\index.js","original":{"line":13,"column":1}},{"name":"document","generated":{"line":20,"column":0},"source":"js\\index.js","original":{"line":14,"column":0}},{"name":"body","generated":{"line":20,"column":9},"source":"js\\index.js","original":{"line":14,"column":9}},{"generated":{"line":20,"column":13},"source":"js\\index.js","original":{"line":14,"column":0}},{"name":"appendChild","generated":{"line":20,"column":14},"source":"js\\index.js","original":{"line":14,"column":14}},{"generated":{"line":20,"column":25},"source":"js\\index.js","original":{"line":14,"column":0}},{"name":"component","generated":{"line":20,"column":26},"source":"js\\index.js","original":{"line":14,"column":26}},{"generated":{"line":20,"column":37},"source":"js\\index.js","original":{"line":14,"column":0}},{"generated":{"line":22,"column":0},"source":"js\\index.js","original":{"line":16,"column":0}},{"generated":{"line":23,"column":0},"source":"js\\index.js","original":{"line":17,"column":0}},{"generated":{"line":24,"column":0},"source":"js\\index.js","original":{"line":18,"column":0}}],"sources":{"js\\index.js":"import shipController from './ships';\n\nconsole.log(shipController.getShips());\nconsole.log(shipController.getShipByName('Executor'));\n\n// check to see if javascript is working\nfunction component() {\n  const element = document.createElement('p');\n\n  element.innerHTML = 'Setup Appears to be working &#128521;';\n\n  return element;\n}\ndocument.body.appendChild(component());\n\n// shipController.getShips().then((data) => {\n//   console.log(data);\n// });\n"},"lineCount":null}},"hash":"80d4bd45229a61eb2b3bb2601abf4a9e","cacheData":{"env":{}}}